Workbook

Sheet Client Details
A4: Client Name
A5: Period Start Date
A6: Period End Date
A8: Trade License Number
A9: Freezone
A10: Mainland
A11: Company Formation Date
A12: License Expiry Date
A13: Business Activities
A14: Owner Names
A16: CTR Number
A17: CT 1st Period
... A25: Format
A26: Font | B26: Aptos
A27: Font Size | B27: 12

Sheet SUMMARY
A1: =+'Client Details'!B4 -> 0
A2: Summary
A4: =TEXT('Client Details'!B5,"DD mmmm YYYY") & " - " & TEXT('Client Details'!B6,"DD mmmm YYYY") -> 30 December 1899 - 30 December 1899
A6: Description | B6: Amount (AED)
A7: Total Revenue | B7: =SoCI!B8 -> 0
A8: Total Expenses (Excluding Director Salary)
A9: Director Salary | B9: =SoCI!B16 -> 0
A10: =IF(B10>0,"Profit","Loss") -> Loss | B10: =SoCI!B31 -> 0
A11: Total Assets | B11: =SoFP!B17 -> 0
A12: Total Liabilities | B12: =SoFP!B30 -> 0
A13: Total Equity | B13: =SoFP!B24 -> 0
A15: Related Party Revenue | B15: =SoCI!B9 -> 0
A16: Related Party Loan
A17: Interest Income
A18: Dividend Income

Sheet SoFP
A1: =+'Client Details'!B4 -> 0
A2: Statement of Financial Position
A4: ="As at " & TEXT('Client Details'!B6,"DD mmmm YYYY") -> As at 30 December 1899
B6: =TEXT('Client Details'!B6,"YYYY") -> 1899 | C6: =B6-1 -> 1898
A7: Assets:
A8: Non-current assets
A9: Property, plant and equipment
A10: Total non-current assets | B10: =SUM(B8:B9) -> 0 | C10: =SUM(C8:C9) -> 0
A11: Current assets
A12: Accounts receivable
A13: Prepayment
A14: VAT recoverable
A15: Cash and bank balances
A16: Total current assets | B16: =SUM(B11:B15) -> 0 | C16: =SUM(C11:C15) -> 0
A17: Total assets | B17: =B16+B10 -> 0 | C17: =C16+C10 -> 0
A19: Equity and Liabilities:
A20: Equity
A21: Share capital
A22: Retained earnings
A23: Owner current account
A24: Total Equity
A25: Non-current liabilities
A26: Long-term loans
A27: Current liabilities
A28: Audit and accounting accrual
A29: VAT payable
A30: Total Liabilities | B30: =SUM(B25:B29) -> 0 | C30: =SUM(C25:C29) -> 0
A31: Total Equity and Liabilities | B31: =B30+B24 -> 0 | C31: =C30+C24 -> 0
B33: =B31-B17 -> 0

Sheet SoCI
A1: =+'Client Details'!B4 -> 0
A2: Statement of Profit and Loss
A4: ="For the year ended " & TEXT('Client Details'!B6,"DD mmmm YYYY") -> For the year ended 30 December 1899
B6: =TEXT('Client Details'!B6,"YYYY") -> 1899 | C6: =B6-1 -> 1898
A8: Revenue
A9: Revenue - related party
A11: Direct cost
A13: Gross profit | B13: =SUM(B9:B11) -> 0 | C13: =SUM(C9:C11) -> 0 | D13: =B13/(B9+B8) -> #DIV/0! | E13: =C13/(C9+C8) -> #DIV/0!
A15: Operating expenses
A16: Director salary
A17: Salaries, wages and benefits
A18: Advertising
A19: Audit and accounting
A24: Bank charges
A25: Exchange loss
A27: Total operating expenses | B27: =SUM(B16:B26) -> 0 | C27: =SUM(C16:C26) -> 0
A29: Other income
A31: Net profit | B31: =B13-B27+B29 -> 0 | C31: =C13-C27+C29 -> 0
A35: Non-deductible expenses
A36: Entertainment | B36: 0.5
A37: Fines and penalties | B37: 1

Sheet SoCE
A1: =+'Client Details'!B4 -> 0
A2: Statement of Changes in Equity
A4: ="For the year ended " & TEXT('Client Details'!B6,"DD mmmm YYYY") -> For the year ended 30 December 1899
B6: Share capital | C6: Owner's current account | D6: Retained earnings | E6: Statutory reserve | F6: Total
A7: Balance as at 00 Month 0000 | F7: =SUM(B7:E7) -> 0
A8: Paid up capital | F8: =SUM(B8:E8) -> 0
A9: Net movement in owner's current account | F9: =SUM(B9:E9) -> 0
A10: Net profit / (loss) | F10: =SUM(B10:E10) -> 0
A11: Transfer to statutory reserve | F11: =SUM(B11:E11) -> 0
A12: ="Balance as at " & TEXT('Client Details'!B5,"DD mmmm YYYY") -> Balance as at 30 December 1899 | B12: =SUM(B7:B11) -> 0 | C12: =SUM(C7:C11) -> 0 | D12: =SUM(D7:D11) -> 0 | E12: =SUM(E7:E11) -> 0 | F12: =SUM(F7:F11) -> 0
A13: Paid up capital | F13: =SUM(B13:E13) -> 0
A14: Net movement in owner's current account | F14: =SUM(B14:E14) -> 0
A15: Net profit / (loss) | F15: =SUM(B15:E15) -> 0
A16: Transfer to statutory reserve | F16: =SUM(B16:E16) -> 0
A17: ="Balance as at " & TEXT('Client Details'!B6,"DD mmmm YYYY") -> Balance as at 30 December 1899 | B17: =SUM(B12:B16) -> 0 | C17: =SUM(C12:C16) -> 0 | D17: =SUM(D12:D16) -> 0 | E17: =SUM(E12:E16) -> 0 | F17: =SUM(F12:F16) -> 0
A22: Statutory reserves

Sheet SoCF
A1: =+'Client Details'!B4 -> 0
A2: Statement of Cash flows
A4: ="For the year ended " & TEXT('Client Details'!B6,"DD mmmm YYYY") -> For the year ended 30 December 1899
B6: =TEXT('Client Details'!B6,"YYYY") -> 1899 | C6: =B6-1 -> 1898
A8: Cash flows from operating activities
A9: Net profit for the year | B9: =SoCI!B31 -> 0
A10: Operating cash flows before changes in working capital | B10: =B9 -> 0 | C10: =C9 -> 0
A11: Changes in working capital
A12: (Increase) / decrease in current assets
A13: Increase / (decrease) in current liabilities
A14: Net cash generated from operations | B14: =SUM(B10:B13) -> 0 | C14: =SUM(C10:C13) -> 0
A15: Cash flows from investing activities
A16: Property, plant and equipment
A17: Net cash generated from investing activities | B17: =SUM(B15:B16) -> 0 | C17: =SUM(C15:C16) -> 0
A18: Cash flows from financing activities
A19: Paid up capital
A20: Owner current account
A21: Net cash generated from financing activities | B21: =SUM(B18:B20) -> 0 | C21: =SUM(C18:C20) -> 0
A22: Net increase in cash and cash equivalents | B22: =B21+B17+B14 -> 0 | C22: =C21+C17+C14 -> 0
A23: Cash and cash equivalents, beginning of the period | B23: =C24 -> 0
A24: Cash and cash equivalents, end of the period | B24: =SUM(B22:B23) -> 0 | C24: =SUM(C22:C23) -> 0

Sheet Prepayment
A1: =+'Client Details'!B4 -> 0
A2: Prepayment
A4: ="For the year ended " & TEXT('Client Details'!B6,"DD mmmm YYYY") -> For the year ended 30 December 1899
A6: Renewed in Current Period
A7: License
A8: Total Amount (AED) | B8: =F23 -> 0
A9: Date of Issuance | B9: 45695
A10: Date of Expiry | B10: 46059
A11: Total Days | B11: =B10-B9+1 -> 365
A12: Cost Per Day | B12: =B8/B11 -> 0
A13: Date of bookkeeping | B13: ='Client Details'!B6 -> 0
A14: Days Expired | B14: =B13-B9+1 -> -45694
A15: Expense | B15: =B12*B14 -> 0
A16: Pre-Payment | B16: =B8-B15 -> 0
A18: Invoice Details for aforementioned working
A19: Inv. Date | B19: Description | C19: Inv No | D19: Gross | E19: VAT | F19: Net
G20: =E22+E23+E24+E25 -> #VALUE!
G21: =E23+E24+E25+E26 -> 0
A22: Description | B22: Quantity | C22: Rate | D22: Taxable Amount | E22: Tax | F22: Amount
B23: 1

Sheet VAT Control
A1: =+'Client Details'!B4 -> 0
A2: VAT Control
A4: ="For the year ended " & TEXT('Client Details'!B6,"DD mmmm YYYY") -> For the year ended 30 December 1899
A6: Description | B6: Dr. | C6: Cr.
A8: Balance b/f
A10: Output VAT
A12: Output VAT on uninvoiced sales
A14: Input VAT on service invoice
A16: Balance c/d
B18: =SUM(B7:B17) -> 0 | C18: =SUM(C7:C17) -> 0 | D18: =B18-C18 -> 0
A20: VAT reconciliation
A22: VAT liability | B22: 0 | C22: =SUM(B22) -> 0
A24: Less: VAT adjustments | B24: 0
A26: B/fwd | B26: 0
C27: =SUM(B27) -> 0
A28: CY
A29: Output VAT on uninvoiced sales | B29: 0
C31: =SUM(C22:C29) -> 0
A33: VAT Summary
A35: Output VAT | B35: Input VAT | C35: VAT Liability | D35: Paid/(Received) | E35: O/S
A36: =C10 -> 0 | B36: =B14 -> 0 | C36: =A36-B36 -> 0 | E36: =C36 -> 0
A37: =SUM(A36:A36) -> 0 | B37: =SUM(B36:B36) -> 0 | D37: =SUM(E29:E36) -> 0 | E37: =SUM(E36:E36) -> 0

Sheet Accruals
A1: =+'Client Details'!B4 -> 0
A2: Accruals
A4: ="For the year ended " & TEXT('Client Details'!B6,"DD mmmm YYYY") -> For the year ended 30 December 1899
B6: Dr. | C6: Cr.
A7: B/F
A8: ="Audit fees " & TEXT('Client Details'!B6,"DD mmmm YYYY") -> Audit fees 30 December 1899
A9: C/F
B10: =SUM(B7:B9) -> 0 | C10: =SUM(C7:C9) -> 0

Sheet Share Capital
A1: =+'Client Details'!B4 -> 0
A2: Share Capital
A4: ="As at " & TEXT('Client Details'!B6,"DD mmmm YYYY") -> As at 30 December 1899
A6: Owner Name | B6: No. of Shares | C6: Value per Share (AED) | D6: Total Share Value (AED)
D7: =B7*C7 -> 0
D8: =B8*C8 -> 0
D9: =B9*C9 -> 0
D10: =B10*C10 -> 0
B11: =SUM(B7:B10) -> 0 | C11: =SUM(C7:C10) -> 0 | D11: =SUM(D7:D10) -> 0
